<?xml version="1.0" ?>
<!-- Licensed to the Apache Software Foundation (ASF) under one or more contributor 
	license agreements. See the NOTICE file distributed with this work for additional 
	information regarding copyright ownership. The ASF licenses this file to 
	You under the Apache License, Version 2.0 (the "License"); you may not use 
	this file except in compliance with the License. You may obtain a copy of 
	the License at http://www.apache.org/licenses/LICENSE-2.0 Unless required 
	by applicable law or agreed to in writing, software distributed under the 
	License is distributed on an "AS IS" BASIS, WITHOUT WARRANTIES OR CONDITIONS 
	OF ANY KIND, either express or implied. See the License for the specific 
	language governing permissions and limitations under the License. -->

<bundles>
	<!-- Stanbol Chain infrastructure and required libraries -->
	<startLevel level="20">
	
		<!-- Camel dependencies -->
		<bundle>
			<groupId>org.apache.camel</groupId>
			<artifactId>camel-core</artifactId>
			<version>2.8.1</version>
		</bundle>

		<bundle>
			<groupId>org.apache.camel</groupId>
			<artifactId>camel-core-osgi</artifactId>
			<version>2.8.1</version>
		</bundle>

		<bundle>
			<groupId>org.fusesource.commonman</groupId>
			<artifactId>commons-management</artifactId>
			<version>1.0</version>
		</bundle>

		<bundle>
			<groupId>org.apache.stanbol</groupId>
			<artifactId>org.apache.stanbol.flow.servicesapi</artifactId>
			<version>0.9.0-incubating-SNAPSHOT</version>
		</bundle>
		
	</startLevel>

	<!-- Web Fragment -->
	<startLevel level="21">
		<bundle>
			<groupId>org.apache.stanbol</groupId>
			<artifactId>org.apache.stanbol.flow.web</artifactId>
			<version>0.9.0-incubating-SNAPSHOT</version>
		</bundle>
	</startLevel>

	<!-- Benchmarks for the Stanbol Enhancer -->
	<startLevel level="21">

	</startLevel>
	
  <!-- Stanbol Enhancer plug-ins (the Enhancement Engines) -->
  <startLevel level="25">
	
  </startLevel>	

	<!-- StartLevel for the chainjobmanager : after engines (level 25 to 26) 
		and before chains (level 29) -->
	<startLevel level="28">
		<bundle>
			<groupId>org.apache.stanbol</groupId>
			<artifactId>org.apache.stanbol.flow.cameljobmanager</artifactId>
			<version>0.9.0-incubating-SNAPSHOT</version>
		</bundle>
	</startLevel>

	<!-- Chain start -->
	<startLevel level="29">
		<!-- filepool chain to activate after -->
		<bundle>
			<groupId>org.apache.stanbol</groupId>
			<artifactId>org.apache.stanbol.flow.filepoolgraphflow</artifactId>
			<version>0.9.0-incubating-SNAPSHOT</version>
		</bundle>
		<bundle>
			<groupId>org.apache.stanbol</groupId>
			<artifactId>org.apache.stanbol.flow.weightedgraphflow</artifactId>
			<version>0.9.0-incubating-SNAPSHOT</version>
		</bundle>
	</startLevel>

</bundles>  
